qb/__main__.py
qb/compiler_functions/__init__.py
qb/compiler_functions/cleaner.py
qb/compiler_functions/keyword_replacement.py
qb/compiler_functions/list_to_collections.py
qb/compiler_functions/mp_helper.py
qb/compiler_functions/multi_line_lambda.py
qb/compiler_functions/pipe_operator.py
qb/compiler_functions/string_cryptography.py
qb-0.1.25.dist-info/entry_points.txt
qb-0.1.25.dist-info/METADATA
qb-0.1.25.dist-info/WHEEL
qb-0.1.25.dist-info/RECORD
