Metadata-Version: 2.3
Name: qb
Version: 0.1.25
Summary: A functional programming language
Author: henceiusegentoo
Author-email: 61363222+henceiusegentoo@users.noreply.github.com
Requires-Python: >=3.13
Classifier: Programming Language :: Python :: 3
Classifier: Programming Language :: Python :: 3.13
Requires-Dist: qb-runtime (>=0.1.0,<0.2.0)
